dml/__init__.py
dml/client.py
dml/exceptions.py
dml/statistics.py
dml/asyncio/__init__.py
dml/asyncio/client.py
dml/asyncio/objects.py
dml/asyncio/statistics.py
dml/metadata/__init__.py
dml/metadata/commands.py
dml/metadata/metadata.py
dml/storage/__init__.py
dml/storage/commands.py
dml/storage/objects.py
dml/storage/selectors.py
dml/storage/storage.py
dml/util/__init__.py
dml/util/buffer.py
tests/__init__.py
tests/conftest.py
tests/test_client.py
tests/test_objects.py
tests/asyncio/__init__.py
tests/asyncio/conftest.py
tests/asyncio/test_client.py
tests/asyncio/test_objects.py
at_uibk_dps_sdkv_client_py-0.0.1.dist-info/METADATA
at_uibk_dps_sdkv_client_py-0.0.1.dist-info/WHEEL
at_uibk_dps_sdkv_client_py-0.0.1.dist-info/entry_points.txt
at_uibk_dps_sdkv_client_py-0.0.1.dist-info/top_level.txt
at_uibk_dps_sdkv_client_py-0.0.1.dist-info/RECORD
