Metadata-Version: 2.1
Name: at-uibk-dps-sdkv-client-py
Version: 0.0.1
Summary: UIBK DPS SDKV Python Package.
Home-page: https://github.com/Apollo-Tools/distributed-data-layer
Project-URL: Bug Tracker, https://github.com/Apollo-Tools/distributed-data-layer/issues
Project-URL: Changelog, https://github.com/Apollo-Tools/distributed-data-layer/releases
Classifier: Programming Language :: Python :: 3
Classifier: License :: OSI Approved :: BSD License
Classifier: Intended Audience :: Developers
Requires-Python: >=3.6
